{
  "main": {
    "id": "798660d7ca39580a",
    "type": "split",
    "children": [
      {
        "id": "35036f1afbe52b5e",
        "type": "tabs",
        "children": [
          {
            "id": "2dc0130e2d438bcc",
            "type": "leaf",
            "state": {
              "type": "markdown",
              "state": {
                "file": "Разное/Покупка квартиры/Осмотр квартиры Грязнова, 3.md",
                "mode": "source",
                "source": false
              },
              "icon": "lucide-file",
              "title": "Осмотр квартиры Грязнова, 3"
            }
          }
        ]
      }
    ],
    "direction": "vertical"
  },
  "left": {
    "id": "8c7826cf8edfb0f3",
    "type": "mobile-drawer",
    "children": [
      {
        "id": "fe8f812e4f66e677",
        "type": "leaf",
        "state": {
          "type": "file-explorer",
          "state": {
            "sortOrder": "alphabetical"
          },
          "icon": "lucide-folder-closed",
          "title": "Files"
        }
      },
      {
        "id": "4a882f005b53a83b",
        "type": "leaf",
        "state": {
          "type": "search",
          "state": {
            "query": "",
            "matchingCase": false,
            "explainSearch": false,
            "collapseAll": false,
            "extraContext": false,
            "sortOrder": "alphabetical"
          },
          "icon": "lucide-search",
          "title": "Search"
        }
      },
      {
        "id": "cb25340e1589221e",
        "type": "leaf",
        "state": {
          "type": "tag",
          "state": {
            "sortOrder": "frequency",
            "useHierarchy": true
          },
          "icon": "lucide-tags",
          "title": "Tags"
        }
      },
      {
        "id": "8175bc7fcd1cfb29",
        "type": "leaf",
        "state": {
          "type": "all-properties",
          "state": {
            "sortOrder": "frequency",
            "showSearch": false,
            "searchQuery": ""
          },
          "icon": "lucide-archive",
          "title": "All properties"
        }
      },
      {
        "id": "64a7910bdc4950ab",
        "type": "leaf",
        "state": {
          "type": "bookmarks",
          "state": {},
          "icon": "lucide-bookmark",
          "title": "Bookmarks"
        }
      }
    ],
    "currentTab": 0
  },
  "right": {
    "id": "3b8c5c135e99ad8f",
    "type": "mobile-drawer",
    "children": [
      {
        "id": "74544934efe6fb82",
        "type": "leaf",
        "state": {
          "type": "backlink",
          "state": {
            "collapseAll": false,
            "extraContext": false,
            "sortOrder": "alphabetical",
            "showSearch": false,
            "searchQuery": "",
            "backlinkCollapsed": false,
            "unlinkedCollapsed": true
          },
          "icon": "links-coming-in",
          "title": "Backlinks"
        }
      },
      {
        "id": "c7a3b13133cc768f",
        "type": "leaf",
        "state": {
          "type": "outgoing-link",
          "state": {
            "linksCollapsed": false,
            "unlinkedCollapsed": true
          },
          "icon": "links-going-out",
          "title": "Outgoing links"
        }
      },
      {
        "id": "43f965882bab7858",
        "type": "leaf",
        "state": {
          "type": "outline",
          "state": {},
          "icon": "lucide-list",
          "title": "Outline"
        }
      },
      {
        "id": "0f1962caef9f1cfe",
        "type": "leaf",
        "state": {
          "type": "copilot-chat-view",
          "state": {},
          "icon": "message-square",
          "title": "Copilot"
        }
      }
    ],
    "currentTab": 3
  },
  "left-ribbon": {
    "hiddenItems": {
      "copilot:Copilot Chat": false,
      "switcher:Open quick switcher": false,
      "graph:Open graph view": false,
      "canvas:Create new canvas": false,
      "daily-notes:Open today's daily note": false,
      "templates:Insert template": false,
      "command-palette:Open command palette": false,
      "whisper:Open recording controls": false
    }
  },
  "active": "2dc0130e2d438bcc",
  "lastOpenFiles": [
    "Разное/Покупка квартиры/Осмотр квартиры на 5-й Армии 31.md",
    "Notion/Разное/Всё про Ксюшу.md",
    "Разработка/Приложение для турка, чтобы управлять сервером русификации.md",
    "Разное/Чек-лист по составлению ежемесячного бюджета.md",
    "Книги/Книги, которые советовал Рустам Амагалиев на AMA.md",
    "Разное/Новый подход к бюджету.md",
    "Разное/Как проверить гипотезу с помощью лендинга и подменного номера.md",
    "Книги/Психология критического мышления.md",
    "Книги/makeright - выжимки из книг.md",
    "Разное/Сколько времени я трачу на бытовые дела.md",
    "Разное/Новое зарядное устройство.md",
    "Продуктивность, GTD и т.д/К прочтению.md",
    "Продуктивность, GTD и т.д/Пост Якутенко про «5 способов быть эффективным».md",
    "Разработка/AI/AI - фронтэнды.md",
    "Разное/Как восстановить доступ к кодам от TBC банка.md",
    "Разработка/AI/Модель phi3.md",
    "Разработка/AI/Open WebUI.md",
    "Разное/Посмотреть medium за пейволом - freedium.cfd.md",
    "Разное/Какой телефон купить.md",
    "Психотерапия/Выводим Ксюшу на чистую воду.md",
    "Разработка/IntelliQ/Issues/Linking with JavaFX forms.md",
    "Продуктивность, GTD и т.д/Как делать ежедневный обзор задач.md",
    "Дневник/2024/2024-10-22 Ксюша встречается с умными и интересными людьми, я ревную.md",
    "Разное/Покупка квартиры/Оформить квартиру на маму и получить налоговый вычет.md",
    "Разное/Покупка квартиры/Как оформлять документы при покупке квартиры.md",
    "Разное/Покупка квартиры/Покупка квартиры.md",
    "Разное/Покупка квартиры",
    "Разное/Подарки",
    "Продуктивность, GTD и т.д/Спринг 12НГ q4",
    "Карьера",
    "Inbox/Telegram/voices/voice_780109839_21 - 20241021163224259.oga",
    "Inbox/Telegram/voices/voice_780109839_22 - 20241021163224485.oga",
    "Inbox/Telegram/voices/voice_780109839_4 - 20241020175104884.oga",
    "Inbox/Telegram/voices/voice_780109839_3 - 20241020174458594.oga",
    "Inbox/Telegram/voices/voice_780109839_6 - 20241021163223173.oga",
    "Inbox/Telegram/voices/voice_780109839_7 - 20241021163223503.oga",
    "Inbox/Telegram/photos/photo_780109839_24 - 20241021163425672.jpg",
    "Inbox/Telegram/photos/photo_780109839_23 - 20241021163224160.jpg",
    "Inbox/Telegram/documents/этапы ремонта - 20241021232056666.png",
    "Продуктивность, GTD и т.д/attachments/3c0.jpg"
  ]
}